okerr/__init__.py
okerr/err.py
okerr/match.py
okerr/ok.py
okerr/result.py
okerr/unwrap_err.py
okerr-0.1.3.dist-info/LICENSE
okerr-0.1.3.dist-info/WHEEL
okerr-0.1.3.dist-info/METADATA
okerr-0.1.3.dist-info/RECORD
