Metadata-Version: 2.1
Name: okerr
Version: 0.1.3
Summary: A simple Result with match functionality for Python
Home-page: https://github.com/ceb10n/okerr
License: MIT
Keywords: result,utility-tool,rust
Author: Rafael Marques
Author-email: rafaelomarques@gmail.com
Maintainer: Rafael Marques
Maintainer-email: rafaelomarques@gmail.com
Requires-Python: >=3.6,<4.0
Classifier: License :: OSI Approved :: MIT License
Classifier: Programming Language :: Python :: 3
Classifier: Programming Language :: Python :: 3.6
Classifier: Programming Language :: Python :: 3.7
Classifier: Programming Language :: Python :: 3.8
Project-URL: Repository, https://github.com/ceb10n/okerr
